mlops_shape_project/__init__.py
mlops_shape_project/data_loader.py
mlops_shape_project/dataframe_checker.py
mlops_shape_project/feature_engineering_predict.py
mlops_shape_project/main.py
mlops_shape_project/pipeline_utils.py
mlops_shape_project/shape.py
mlops_shape_project-0.3.2.dist-info/entry_points.txt
mlops_shape_project-0.3.2.dist-info/METADATA
mlops_shape_project-0.3.2.dist-info/WHEEL
mlops_shape_project-0.3.2.dist-info/RECORD
