Metadata-Version: 2.1
Name: mlops-shape-project
Version: 0.3.2
Summary: This project was initiated as part of Shape's Hard Skill Test for the Machine Learning Engineer role. The core objective was to take an initial script named `job_test_challenge.py` and transform it into a more organized 📐, maintainable 🛠️, and production-ready codebase.
License: MIT
Author: Junior Torres
Author-email: galas.apps@gmail.com
Requires-Python: >=3.8.10,<4.0.0
Classifier: Development Status :: 4 - Beta
Classifier: License :: OSI Approved :: MIT License
Classifier: Natural Language :: English
Classifier: Programming Language :: Python :: 3
Classifier: Programming Language :: Python :: 3.9
Classifier: Programming Language :: Python :: 3.10
Classifier: Programming Language :: Python :: 3.11
Classifier: Programming Language :: Python :: 3.8
Classifier: Topic :: Scientific/Engineering :: Artificial Intelligence
Classifier: Topic :: Software Development :: Libraries :: Python Modules
Requires-Dist: fastapi[all] (>=0.100.1,<0.101.0)
Requires-Dist: pyarrow (>=12.0.1,<13.0.0)
Requires-Dist: pydantic (>=2.1.1,<3.0.0)
Requires-Dist: python-multipart (>=0.0.6,<0.0.7)
Requires-Dist: scikit-learn (==1.0.2)
Requires-Dist: uvicorn (>=0.23.2,<0.24.0)
Project-URL: Code, https://github.com/JuniorTorresMTJ/mlops_shape_project
Project-URL: Documentation, https://mlops-shape-project.readthedocs.io/en/latest/
